LICENSE.md
MANIFEST.in
README.md
setup.py
eQTLseq/ModelBinom.py
eQTLseq/ModelNBinom.py
eQTLseq/ModelNormal.py
eQTLseq/ModelPoisson.py
eQTLseq/__init__.py
eQTLseq/alg.py
eQTLseq/common.py
eQTLseq/common_nb.py
eQTLseq/driver.py
eQTLseq/parallel.py
eQTLseq/sim.py
eQTLseq/trans.py
eQTLseq/utils.py
eQTLseq.egg-info/PKG-INFO
eQTLseq.egg-info/SOURCES.txt
eQTLseq.egg-info/dependency_links.txt
eQTLseq.egg-info/requires.txt
eQTLseq.egg-info/top_level.txt