Metadata-Version: 1.1
Name: eQTLseq
Version: 17.5.28
Summary: Hierarchical probabilistic models for multiple gene/variant associations based on NGS data
Home-page: https://github.com/dvav/eQTLseq
Author: Dimitrios V. Vavoulis
Author-email: Dimitris.Vavoulis@ndcls.well.ox.ac.uk
License: MIT
Keywords: eQTL Bayesian RNA-seq
Platform: UNIX
Classifier: Development Status :: 5 - Production/Stable
Classifier: Environment :: Console
Classifier: Intended Audience :: Science/Research
Classifier: License :: OSI Approved :: MIT License
Classifier: Operating System :: Unix
Classifier: Programming Language :: Python :: 3.5
Classifier: Topic :: Scientific/Engineering :: Bio-Informatics
